proto2json/__init__.py
proto2json/decoder.py
proto2json-1.0.0.dist-info/LICENSE
proto2json-1.0.0.dist-info/METADATA
proto2json-1.0.0.dist-info/WHEEL
proto2json-1.0.0.dist-info/top_level.txt
proto2json-1.0.0.dist-info/RECORD
