Metadata-Version: 2.1
Name: proto2json
Version: 1.0.0
Summary: Decode protobuf binary data to JSON without schema definition
Home-page: https://github.com/ljt270864457/proto2json
Author: Liu Jiatian
Author-email: Liu Jiatian <liujiatian.cool@gmail.com>
License: MIT
Project-URL: Homepage, https://github.com/ljt270864457/proto2json
Project-URL: Repository, https://github.com/ljt270864457/proto2json
Project-URL: Bug Tracker, https://github.com/ljt270864457/proto2json/issues
Keywords: protobuf,json,decoder,protocol-buffers,protobuf-decoder
Classifier: Development Status :: 4 - Beta
Classifier: Intended Audience :: Developers
Classifier: License :: OSI Approved :: MIT License
Classifier: Programming Language :: Python :: 3
Classifier: Programming Language :: Python :: 3.7
Classifier: Programming Language :: Python :: 3.8
Classifier: Programming Language :: Python :: 3.9
Classifier: Programming Language :: Python :: 3.10
Classifier: Programming Language :: Python :: 3.11
Classifier: Programming Language :: Python :: 3.12
Classifier: Topic :: Software Development :: Libraries :: Python Modules
Classifier: Topic :: Utilities
Requires-Python: >=3.7
License-File: LICENSE
